openquantum_sdk_qiskit/__init__.py
openquantum_sdk_qiskit/_qasm.py
openquantum_sdk_qiskit/backend_data.py
openquantum_sdk_qiskit/oq_backend.py
openquantum_sdk_qiskit/oq_estimator.py
openquantum_sdk_qiskit/oq_sampler.py
openquantum_sdk_qiskit/oq_service.py
openquantum_sdk_qiskit/oq_target.py
openquantum_sdk_qiskit-0.2.2.dist-info/METADATA
openquantum_sdk_qiskit-0.2.2.dist-info/WHEEL
openquantum_sdk_qiskit-0.2.2.dist-info/top_level.txt
openquantum_sdk_qiskit-0.2.2.dist-info/RECORD
