Metadata-Version: 2.4
Name: openquantum-sdk-qiskit
Version: 0.2.2
Summary: Qiskit Python SDK for Open Quantum
Classifier: Programming Language :: Python :: 3
Classifier: License :: OSI Approved :: Apache Software License
Classifier: Operating System :: OS Independent
Requires-Python: >=3.9
Requires-Dist: openquantum-sdk>=0.3.1
Requires-Dist: qiskit>=2.0.0
